qtoggleserver/raspigpio/__init__.py
qtoggleserver/raspigpio/raspigpio.py
qtoggleserver_raspigpio-1.2.0.dist-info/licenses/LICENSE.txt
qtoggleserver_raspigpio-1.2.0.dist-info/METADATA
qtoggleserver_raspigpio-1.2.0.dist-info/WHEEL
qtoggleserver_raspigpio-1.2.0.dist-info/top_level.txt
qtoggleserver_raspigpio-1.2.0.dist-info/RECORD
