Metadata-Version: 2.4
Name: qtoggleserver-raspigpio
Version: 1.2.0
Summary: qToggleServer driver for Raspberry Pi GPIOs based on raspi-gpio
Author-email: Calin Crisan <ccrisan@gmail.com>
License: Apache 2.0
Requires-Python: >=3.11
License-File: LICENSE.txt
Dynamic: license-file
